{
  "task": [
    {
      "taskName": "Quas doloribus ullam",
      "priority": "Low",
      "status": "Todo",
      "deadline": "1994-01-02",
      "message": "Eos elit id mollit",
      "id": 1
    },
    {
      "taskName": "Reprehenderit anim l",
      "priority": "Medium",
      "status": "Doing",
      "deadline": "1993-11-09",
      "message": "Blanditiis reprehend",
      "id": 2
    },
    {
      "taskName": "Eveniet molestiae e",
      "priority": "Hight",
      "status": "Done",
      "deadline": "1987-10-19",
      "message": "Ex inventore dolor m",
      "id": 3
    },
    {
      "taskName": "Ad fugit eiusmod co",
      "priority": "Low",
      "status": "Done",
      "deadline": "2023-03-20",
      "message": "",
      "id": 4
    }
  ]
}